{
  "projects": [
    {
      "name": "saber2pr.github.io",
      "href": "https://github.com/Saber2pr/saber2pr.github.io",
      "content": "saber2pr's website."
    },
    {
      "name": "editor",
      "href": "https://github.com/Saber2pr/editor",
      "content": "a web editor powered by monaco-editor."
    },
    {
      "name": "next-tpl",
      "href": "https://github.com/Saber2pr/next-tpl",
      "content": "next.js + antd + axios + docker."
    },
    {
      "name": "@saber2pr/ptbk",
      "href": "https://github.com/Saber2pr/ptbk",
      "content": "encode & decode"
    },
    {
      "name": "@saber2pr/react",
      "href": "https://github.com/Saber2pr/react",
      "content": "React-Like in Typescript."
    },
    {
      "name": "@saber2pr/ioc",
      "href": "https://github.com/Saber2pr/saber-ioc",
      "content": "Injector for Typescript IOC."
    },
    {
      "name": "@saber2pr/reflect",
      "href": "https://github.com/Saber2pr/-saber2pr-reflect",
      "content": "Typescript Reflector."
    }
  ]
}